{"cameraMode":{"drawMode":0,"name":"Shaded","section":"Shading Mode"},"sceneLighting":true,"audioPlay":false,"sceneViewState":{"m_AlwaysRefresh":false,"showFog":true,"showSkybox":true,"showFlares":true,"showImageEffects":true,"showParticleSystems":true,"showVisualEffectGraphs":true,"m_FxEnabled":true},"in2DMode":false,"pivot":{"x":2.3211405277252199,"y":-1.460920810699463,"z":28.723743438720704},"rotation":{"x":0.03925228491425514,"y":0.03149048238992691,"z":0.00913710705935955,"w":0.9986777305603027},"size":19.470056533813478,"orthographic":false}